dicom_anonymiser/__init__.py
dicom_anonymiser/__main__.py
dicom_anonymiser/tools.py
dicom_anonymiser/tags/default_tags.csv
dicom_anonymiser/tags/meta_tags.csv
dicom_anonymiser/tags/user_tags.csv
dicom_anonymiser-0.2.5.dist-info/LICENSE.txt
dicom_anonymiser-0.2.5.dist-info/METADATA
dicom_anonymiser-0.2.5.dist-info/WHEEL
dicom_anonymiser-0.2.5.dist-info/entry_points.txt
dicom_anonymiser-0.2.5.dist-info/top_level.txt
dicom_anonymiser-0.2.5.dist-info/RECORD
